pybind11_mkdoc/__init__.py
pybind11_mkdoc/__main__.py
pybind11_mkdoc/mkdoc_lib.py
pybind11_mkdoc-2.6.2.dist-info/entry_points.txt
pybind11_mkdoc-2.6.2.dist-info/LICENSE
pybind11_mkdoc-2.6.2.dist-info/WHEEL
pybind11_mkdoc-2.6.2.dist-info/METADATA
pybind11_mkdoc-2.6.2.dist-info/RECORD
